README.rst
setup.py
Flask_APScheduler_fork.egg-info/PKG-INFO
Flask_APScheduler_fork.egg-info/SOURCES.txt
Flask_APScheduler_fork.egg-info/dependency_links.txt
Flask_APScheduler_fork.egg-info/requires.txt
Flask_APScheduler_fork.egg-info/top_level.txt
flask_apscheduler/__init__.py
flask_apscheduler/api.py
flask_apscheduler/auth.py
flask_apscheduler/json.py
flask_apscheduler/scheduler.py
flask_apscheduler/utils.py