Metadata-Version: 1.1
Name: Flask-APScheduler_fork
Version: 1.5.4
Summary: Test package and a fork of flask_apscheduler.
Home-page: https://github.com/eayin2/flask-apscheduler
Author: Eayin
Author-email: eayin2@gmail.com
License: Apache 2.0
Keywords: apscheduler,scheduler,scheduling,cron
Platform: UNKNOWN
Classifier: Development Status :: 5 - Production/Stable
Classifier: Intended Audience :: Developers
Classifier: Natural Language :: English
Classifier: Operating System :: OS Independent
Classifier: Programming Language :: Python
Classifier: Programming Language :: Python :: 2.7
Classifier: Programming Language :: Python :: 3
Classifier: Programming Language :: Python :: 3.3
Classifier: Programming Language :: Python :: 3.4
Classifier: Programming Language :: Python :: 3.5
